Workbook
Name aporte: MANGGAINVEST!$D$18
Name patrimonio: MANGGAINVEST!$D$21
Name qtd_anos: MANGGAINVEST!$D$19
Name rendimento_carteira: MANGGAINVEST!$D$14
Name salario: MANGGAINVEST!$D$13
Name sugestao_investimento: MANGGAINVEST!$D$15
Name taxa_mensal: MANGGAINVEST!$D$20

Sheet MANGGAINVEST
B12: CONFIGURAÇÕES
B13: Salário | D13: 5000
B14: Rendimento Carteira | D14: 0.006
B15: Sugestão de Investimento (30%) | D15: =D13*30% -> 1500
B17: INVESTIMENTO MENSAL
B18: Quanto investir por mês? | D18: 500
B19: Por quantos anos? | D19: 5
B20: Qual a taxa de rendimento mensal? | D20: 0.01079
B21: Patrimônio Acumulado? | D21: =FV(taxa_mensal,qtd_anos*12,aporte*-1) -> 41888.457
B22: Dividendos mensais? | D22: =patrimonio*rendimento_carteira -> 251.33074
B24: CENÁRIOS | D24: DIVIDENDOS
A25: 2 | B25: Quanto em 2 Anos? | C25: =FV($D$20,$A25*12,$D$18*-1) -> 13613.814 | D25: =C25*rendimento_carteira -> 81.682882
A26: 5 | B26: Quanto em 5 Anos? | C26: =FV($D$20,$A26*12,$D$18*-1) -> 41888.457 | D26: =C26*rendimento_carteira -> 251.33074
A27: 10 | B27: Quanto em 10 Anos | C27: =FV($D$20,$A27*12,$D$18*-1) -> 121642.11 | D27: =C27*rendimento_carteira -> 729.85264
A28: 20 | B28: Quanto em 20 Anos? | C28: =FV($D$20,$A28*12,$D$18*-1) -> 562599.2 | D28: =C28*rendimento_carteira -> 3375.5952
A29: 30 | B29: Quanto em 30 Anos? | C29: =FV($D$20,$A29*12,$D$18*-1) -> 2161084.8 | D29: =C29*rendimento_carteira -> 12966.509
B31: PERFIL | C31: MODERADO
B32: Valor a ser investido por mês | C32: 500
B34: TIPO DE FII | C34: Percentual Sugerido | D34: Valores
B35: Papel | C35: =VLOOKUP($C$31&"-"&B35,APOIO!$A:$D,4,FALSE) -> 0.32 | D35: =C35*$C$32 -> 160
B36: Tijolo | C36: =VLOOKUP($C$31&"-"&B36,APOIO!$A:$D,4,FALSE) -> 0.35 | D36: =C36*$C$32 -> 175
B37: Híbridos | C37: =VLOOKUP($C$31&"-"&B37,APOIO!$A:$D,4,FALSE) -> 0.08 | D37: =C37*$C$32 -> 40
B38: FOFs | C38: =VLOOKUP($C$31&"-"&B38,APOIO!$A:$D,4,FALSE) -> 0.05 | D38: =C38*$C$32 -> 25
B39: Desenvolvimento | C39: =VLOOKUP($C$31&"-"&B39,APOIO!$A:$D,4,FALSE) -> 0.1 | D39: =C39*$C$32 -> 50
B40: Hotelarias | C40: =VLOOKUP($C$31&"-"&B40,APOIO!$A:$D,4,FALSE) -> 0.1 | D40: =C40*$C$32 -> 50
D41: =SUM(D35:D40) -> 500

Sheet APOIO
A2: CHAVE COMPOSTA | B2: PERFIL | C2: TIPO DE FII | D2: %
A3: =$B3&"-"&C3 -> CONSERVADOR-Papel | B3: CONSERVADOR | C3: Papel | D3: 0.3
A4: =$B4&"-"&C4 -> CONSERVADOR-Tijolo | B4: CONSERVADOR | C4: Tijolo | D4: 0.5
A5: =$B5&"-"&C5 -> CONSERVADOR-Híbridos | B5: CONSERVADOR | C5: Híbridos | D5: 0.1
A6: =$B6&"-"&C6 -> CONSERVADOR-FOFs | B6: CONSERVADOR | C6: FOFs | D6: 0.1
A7: =$B7&"-"&C7 -> CONSERVADOR-Desenvolvimento | B7: CONSERVADOR | C7: Desenvolvimento | D7: 0
A8: =$B8&"-"&C8 -> CONSERVADOR-Hotelarias | B8: CONSERVADOR | C8: Hotelarias | D8: 0
A9: =$B9&"-"&C9 -> MODERADO-Papel | B9: MODERADO | C9: Papel | D9: 0.32
A10: =$B10&"-"&C10 -> MODERADO-Tijolo | B10: MODERADO | C10: Tijolo | D10: 0.35
A11: =$B11&"-"&C11 -> MODERADO-Híbridos | B11: MODERADO | C11: Híbridos | D11: 0.08
A12: =$B12&"-"&C12 -> MODERADO-FOFs | B12: MODERADO | C12: FOFs | D12: 0.05
A13: =$B13&"-"&C13 -> MODERADO-Desenvolvimento | B13: MODERADO | C13: Desenvolvimento | D13: 0.1
A14: =$B14&"-"&C14 -> MODERADO-Hotelarias | B14: MODERADO | C14: Hotelarias | D14: 0.1
... A20: =$B20&"-"&C20 -> AGRESSIVO-Hotelarias | B20: AGRESSIVO | C20: Hotelarias | D20: 0.1
